{"isbn":"9666965348","author":"Strugatskie","name":"Grad obrechenniy","total":"10","available":"5"},
{"isbn":"5845908914","author":"Kernigan, Ritchi","name":"Yazik programmirovaniya C","total":"13","available":"10"},
{"isbn":"1666965348","author":"Strugatskie","name":"Grad obrechenniy","total":"10","available":"5"},
{"isbn":"5845934514","author":"Ritchi","name":"Yazik programmirovaniya C","total":"13","available":"10"},
{"isbn":"5846934514","author":"Ritchi","name":"Yazik programmirovaniya C","total":"13","available":"10"},
